{
  "builders": [
    {
      "disk_size": "{{user `disk_size`}}",
      "floppy_files": [
        "floppy/win81x86-enterprise/Autounattend.xml",
        "floppy/00-run-all-scripts.cmd",
        "floppy/install-winrm.cmd",
        "floppy/powerconfig.bat",
        "floppy/01-install-wget.cmd",
        "floppy/_download.cmd",
        "floppy/_packer_config.cmd",
        "floppy/passwordchange.bat",
        "floppy/cygwin.sh",
        "floppy/cygwin.bat",
        "floppy/zz-start-sshd.cmd"
      ],
      "guest_os_type": "windows8",
      "headless": "{{ user `headless` }}",
      "iso_checksum": "{{ user `iso_checksum` }}",
      "iso_checksum_type": "sha1",
      "iso_url": "{{ user `iso_url` }}",
      "shutdown_command": "{{ user `shutdown_command`}}",
      "ssh_password": "vagrant",
      "ssh_username": "vagrant",
      "ssh_wait_timeout": "10000s",
      "tools_upload_flavor": "windows",
      "type": "vmware-iso",
      "vm_name": "win81x86-enterprise-cygwin",
      "vmx_data": {
        "cpuid.coresPerSocket": "1",
        "memsize": "1536",
        "numvcpus": "1",
        "scsi0.virtualDev": "lsisas1068"
      }
    },
    {
      "disk_size": "{{user `disk_size`}}",
      "floppy_files": [
        "floppy/win81x86-enterprise/Autounattend.xml",
        "floppy/00-run-all-scripts.cmd",
        "floppy/install-winrm.cmd",
        "floppy/powerconfig.bat",
        "floppy/01-install-wget.cmd",
        "floppy/_download.cmd",
        "floppy/_packer_config.cmd",
        "floppy/passwordchange.bat",
        "floppy/cygwin.sh",
        "floppy/cygwin.bat",
        "floppy/zz-start-sshd.cmd",
        "floppy/oracle-cert.cer"
      ],
      "guest_additions_mode": "attach",
      "guest_os_type": "Windows8",
      "hard_drive_interface": "sata",
      "headless": "{{ user `headless` }}",
      "iso_checksum": "{{ user `iso_checksum` }}",
      "iso_checksum_type": "sha1",
      "iso_url": "{{ user `iso_url` }}",
      "shutdown_command": "{{ user `shutdown_command`}}",
      "post_shutdown_delay": "30s",
      "ssh_password": "vagrant",
      "ssh_username": "vagrant",
      "ssh_wait_timeout": "10000s",
      "type": "virtualbox-iso",
      "vboxmanage": [
        [
          "modifyvm",
          "{{.Name}}",
          "--memory",
          "1536"
        ],
        [
          "modifyvm",
          "{{.Name}}",
          "--cpus",
          "1"
        ]
      ],
      "vm_name": "win81x86-enterprise-cygwin"
    },
    {
      "disk_size": "{{user `disk_size`}}",
      "floppy_files": [
        "floppy/win81x86-enterprise/Autounattend.xml",
        "floppy/00-run-all-scripts.cmd",
        "floppy/install-winrm.cmd",
        "floppy/powerconfig.bat",
        "floppy/01-install-wget.cmd",
        "floppy/_download.cmd",
        "floppy/_packer_config.cmd",
        "floppy/passwordchange.bat",
        "floppy/cygwin.sh",
        "floppy/cygwin.bat",
        "floppy/zz-start-sshd.cmd"
      ],
      "guest_os_type": "win-8.1",
      "iso_checksum": "{{ user `iso_checksum` }}",
      "iso_checksum_type": "sha1",
      "iso_url": "{{ user `iso_url` }}",
      "parallels_tools_flavor": "win",
      "prlctl": [
        [
          "set",
          "{{.Name}}",
          "--memsize",
          "1536"
        ],
        [
          "set",
          "{{.Name}}",
          "--cpus",
          "1"
        ]
      ],
      "shutdown_command": "{{ user `shutdown_command`}}",
      "ssh_password": "vagrant",
      "ssh_username": "vagrant",
      "ssh_wait_timeout": "10000s",
      "type": "parallels-iso",
      "vm_name": "win81x86-enterprise-cygwin"
    }
  ],
  "post-processors": [
    {
      "compression_level": 1,
      "keep_input_artifact": false,
      "output": "box/{{.Provider}}/win81x86-enterprise-cygwin-{{user `cm`}}{{user `cm_version`}}-{{user `version`}}.box",
      "type": "vagrant",
      "vagrantfile_template": "tpl/vagrantfile-win81x86-enterprise-cygwin.tpl"
    }
  ],
  "provisioners": [
    {
      "environment_vars": [
        "CM={{user `cm`}}",
        "CM_VERSION={{user `cm_version`}}",
        "UPDATE={{user `update`}}"
      ],
      "execute_command": "{{.Vars}} cmd /c $(/bin/cygpath -m '{{.Path}}')",
      "remote_path": "C:/Windows/Temp/script.bat",
      "scripts": [
        "script/vagrant.bat",
        "script/cmtool.bat",
        "script/vmtool.bat",
        "script/clean.bat",
        "script/ultradefrag.bat",
        "script/uninstall-7zip.bat",
        "script/sdelete.bat"
      ],
      "type": "shell"
    },
    {
      "inline": [
        "rm -f /cygdrive/c/Windows/Temp/script.bat"
      ],
      "type": "shell"
    }
  ],
  "variables": {
    "cm": "chef",
    "cm_version": "",
    "disk_size": "40960",
    "headless": "false",
    "iso_checksum": "fe43558b4708b4b786bc3286924813b0aad21106",
    "iso_url": "iso/en_windows_8.1_enterprise_with_update_x86_dvd_4065185.iso",
    "shutdown_command": "shutdown /s /t 10 /f /d p:4:1 /c 'Packer Shutdown'",
    "update": "true",
    "version": "0.1.0"
  }
}

